setup.py
pydream/__init__.py
pydream/display.py
pydream_led.egg-info/PKG-INFO
pydream_led.egg-info/SOURCES.txt
pydream_led.egg-info/dependency_links.txt
pydream_led.egg-info/requires.txt
pydream_led.egg-info/top_level.txt