Metadata-Version: 1.0
Name: pydream-led
Version: 0.1.1
Summary: PyDream - driver for Dream Cheeky 21x7 LED display (VendorId: 0x1d34 DeviceId: 0x001
Home-page: https://github.com/darrenpmeyer/pydream-led
Author: Darren P Meyer
Author-email: darren@darrenpmeyer.com
License: UNKNOWN
Platform: UNKNOWN
